Workbook

Sheet README
A1: Lumio Analytics - Synthetic Treasury Dataset
A2: Built for the Razorpay AI PM Build Challenge prototype (EEFC conversion-planning agent)
A4: ALL DATA IN THIS WORKBOOK IS SYNTHETIC. Company, clients, vendors and the USD/INR rate path are fictional; rules and cost assumptions are listed below.
A6: Assumption | B6: Value
A7: Merchant | B7: Lumio Analytics Pvt Ltd (fictional) - Bengaluru B2B SaaS, bills US clients in USD via Razorpay
A8: Scenario date (today) | B8: 2026-10-26
A9: History window | B9: 2024-11-01 to 2026-10-26 (24 months)
A10: EEFC holding switched on | B10: 2026-09-01 (before this, every USD receipt was converted to INR at settlement)
A11: Inbound conversion | B11: Razorpay live mid-market rate, 0% FX markup (per Razorpay's published MoneySaver pricing); platform fee ignored as it is identical in both scenarios
A12: Outward FX via corporate card (AWS, tools) | B12: 3.0% all-in markup over mid (assumption; Indian business cards typically 2-3.5%)
A13: Outward FX via bank wire (contractor) | B13: 0.9% markup over mid + Rs 1,200 flat charge per wire (assumption)
A14: EEFC rule | B14: Accruals in a calendar month must be converted to INR by the last day of the following month, after USD used for permitted payments (RBI Master Direction - Deposits and Accounts)
A15: USD/INR | B15: Synthetic daily mid-rate path (business days), ~84.1 to ~88.4; NOT real market data
A16: INR safety buffer policy | B16: Rs 8,00,000 minimum in INR current account (merchant setting)
A17: Confidence score | B17: Illustrative heuristic = history depth x timing regularity x amount stability (see Demo_Scenario notes)
A19: Story in one line
A20: For 22 months Lumio converted every USD receipt to INR at settlement, then bought USD back to pay AWS, tools and a US contractor. On 1 Sep 2026 it switched on EEFC settlement and now holds USD, but manages conversions by hand (one manual conversion on 29 Sep). On 26 Oct 2026 ('today') it has USD in two EEFC buckets, an INR balance sitting at its buffer, payroll in 7 days and a September deadline in 5.
A22: Sheet | B22: What it holds
A23: Demo_Scenario | B23: Today's position, the agent's 6 expected outputs (locked / green / amber / red) and the use-case coverage checklist
A24: Value_at_Stake | B24: Baseline (convert at settlement) vs netting from EEFC - live formulas
A25: Monthly_Summary | B25: 24-month roll-up of receipts, conversions, outflows and balances - live formulas over the data sheets
A26: Detected_Patterns | B26: Recurring obligations the agent infers from history, with confidence and its components
A27: Client_Behaviour | B27: Payment timing per client (on-time, late payer, new client, churned, annual)
A28: Receipts | B28: Every USD invoice: issued, due, paid / outstanding / scheduled
A29: INR_Outflows | B29: Payroll, rent, GST, advance tax, fees, one-offs, FD sweeps (non-operating)
A30: USD_Outflows | B30: AWS, tools, contractor - how each was paid and the avoidable FX cost
A31: Conversions | B31: Every USD to INR conversion (auto at settlement, then manual from EEFC)
A32: EEFC_Ledger | B32: Credits and debits by monthly bucket since EEFC was switched on
A33: Daily_Balances | B33: INR current-account and EEFC USD balance, every day
... A35: Clients | B35: Client master

Sheet Demo_Scenario
A1: Scenario: Monday 26 Oct 2026
A2: Agent's expected outputs for the prototype. Confidence = forecast confidence in the cash inputs, not a rate prediction.
A4: Position today
A5: Item | B5: Value | C5: Note
A6: INR current account (Rs) | B6: 856293 | C6: At the Rs 8L buffer policy
A7: USD/INR today | B7: 88.42 | C7: Synthetic
A8: EEFC Sep-2026 bucket (USD) | B8: 21332.42 | C8: Deadline 31 Oct 2026 - 5 days left
A9: EEFC Oct-2026 bucket (USD) | B9: 71190 | C9: Deadline 30 Nov 2026 - 35 days left
A10: Next payroll | B10: Mon 2 Nov 2026 | C10: ~Rs 37.1L
A12: Agent plan (expected outputs)
A13: ID | B13: Type | C13: Title | D13: Action | E13: USD | F13: Est. INR | G13: Deadline / timing | H13: Confidence % | I13: Band | J13: Agent reasoning | K13: Input flagged for review | L13: What the merchant can do
A14: R1 | B14: LOCKED - deadline rule | C14: Convert the remaining September balance | D14: Convert USD 21,332 from the Sep-2026 bucket on Fri 30 Oct 2026 | E14: 21332.42 | F14: 1886213 | G14: 2026-10-31 (Sat) - executes Fri 30 Oct | I14: Locked | J14: RBI EEFC rule: September accruals must be converted by the last day of October. 31 Oct is a Saturday, so the agent schedules Friday. Cannot be skipped; amount is the unutilised balance. | L14: View / change execution time only (must be on or before 30 Oct)
A15: R2 | B15: Recommendation | C15: Fund the 2 Nov payroll and 5 Nov rent | D15: Convert USD 23,800 from the Oct-2026 bucket on Thu 29 Oct 2026 | E15: 23800 | F15: 2104396 | G15: Before 2 Nov payroll | H15: 93 | I15: High | J15: Payroll ~INR 37.1L (24 of 24 months on the 1st/next business day) + rent INR 3.36L + INR 8L buffer, minus current INR balance INR 8.56L and the locked Sep conversion (~INR 18.9L). | L15: Approve / edit amount or date / skip
A16: R3 | B16: Recommendation | C16: Hold USD for AWS and tools - do not convert | D16: Keep USD 9,700 in EEFC to pay AWS (3 Nov) and tools (9 Nov) directly in USD | E16: 9700 | F16: 0 | G16: 3 Nov / 9 Nov | H16: 67 | I16: Medium | J16: Paying from USD avoids buying dollars back at ~3% card markup (~INR 25.7k saved). AWS estimate USD 7,278 (range 6,186-8,369); held amount covers the top of the range. | K16: AWS bill amount - Oct was 31% above the prior 5-month average | L16: Confirm expected AWS bill, then approve / edit / skip
A17: R4 | B17: Question (low confidence) | C17: Will the team offsite recur this November? | D17: No conversion proposed until answered | F17: 420000 | G17: Answer before ~10 Nov | H17: 17 | I17: Low | J17: An INR 4.2L payment to Coorg Retreats appeared once (14 Nov 2025). One occurrence is not enough to forecast it, so the agent asks instead of guessing. | K17: Is this a recurring annual expense? | L17: Yes (adds INR 4.2L to the Nov plan) / No / Not sure (agent keeps extra buffer)
A18: R5 | B18: Planned - deadline rule + AI timing | C18: Convert the rest of the October balance in 2 tranches | D18: Convert USD 18,800 on Mon 16 Nov and USD 18,890 on Thu 26 Nov | E18: 37690 | F18: 3332550 | G18: 2026-11-30 (Oct accruals) | I18: Locked | J18: October accruals must be converted by 30 Nov. Splitting into two dates avoids converting the whole balance at a single day's rate; the INR funds GST (20 Nov) and the 1 Dec payroll. | L18: Change tranche dates/split (all must complete by 30 Nov)
A19: R6 | B19: Recommendation | C19: Top up for the 1 Dec payroll from November receipts | D19: Convert ~USD 6,300 from November receipts around 27 Nov | E19: 6300 | F19: 557046 | G19: Before 1 Dec payroll | H19: 67 | I19: Medium | J19: Depends on ~USD 45,450 from on-time clients (reliable), plus Atlas Freight USD 17,110 (new client, only 3 payments seen) and Brightpath's overdue Oct invoice USD 8,630 (habitually 30-45 days late). | K19: Timing of Atlas Freight (new) and Brightpath Health (late payer) receipts | L19: Confirm whether Atlas/Brightpath payments are expected, then approve / edit / skip
A21: Bands
A22: Band | B22: Rule | C22: Behaviour
A23: High | B23: >= 80% | C23: Quick approve: one summary card, then app authentication
A24: Medium | B24: 50-79% | C24: Flagged input shown; merchant confirms/edits it, then authenticates
A25: Low | B25: < 50% | C25: No recommendation - the agent asks a question first
A26: Locked | B26: Rule-driven | C26: EEFC deadline conversions; no score; cannot be skipped
A29: Use-case coverage checklist
A30: Case | B30: Where it appears
A31: Locked deadline conversion (no confidence score) | B31: R1, R5
A32: High-confidence recommendation (green) | B32: R2
A33: Medium confidence with flagged input (amber) | B33: R3, R6
A34: Low confidence -> agent asks a question (red) | B34: R4
A35: Netting USD payables instead of converting | B35: R3
A36: Recurring obligations detected from 24 months of history | B36: Detected_Patterns sheet
A37: Non-operating flow correctly ignored (FD sweeps, one-off equipment) | B37: INR_Outflows: Sweep to fixed deposit / Equipment
A38: Late-paying client | B38: Brightpath Health (C02)
A39: New large client with thin history | B39: Atlas Freight Partners (C11)
A40: Churned client (agent must not forecast its receipts) | B40: Cedar & Finch Retail (C03)
A41: Annual prepayment spikes | B41: Northgate (Jan), Bluefjord (Jul)
... A43: Baseline vs agent value | B43: Value_at_Stake sheet

Sheet Value_at_Stake
A1: Value at stake - netting USD costs from EEFC
A2: Formulas read the USD_Outflows sheet. Blue = assumption you can change on README / generator.
A3: Metric | B3: Value | C3: Note
A4: EEFC switched on (date) | B4: 46266 | C4: Input
A5: Months of convert-at-settlement history | B5: 22 | C5: Input
A6: USD costs paid by buying USD back (USD) | B6: =SUMIFS(USD_Outflows!$D:$D,USD_Outflows!$A:$A,"<"&B4) -> 192114.33
A7: INR spent on those USD costs (Rs) | B7: =SUMIFS(USD_Outflows!$I:$I,USD_Outflows!$A:$A,"<"&B4) -> 16914283
A8: Avoidable FX cost - markups + wire fees (Rs) | B8: =SUMIFS(USD_Outflows!$J:$J,USD_Outflows!$A:$A,"<"&B4) -> 390488.95
A9: Avoidable FX cost, annualised (Rs / yr) | B9: =B8/B5*12 -> 212993.97
A10: As % of USD costs | B10: =B8/B7 -> 0.023086343
A11: Since EEFC: USD costs paid directly from EEFC (USD) | B11: =SUMIFS(USD_Outflows!$D:$D,USD_Outflows!$A:$A,">="&B4,USD_Outflows!$G:$G,"EEFC (USD)") -> 18857.58
A12: Since EEFC: still paid by card (EEFC empty on 3 Sep) (USD) | B12: =SUMIFS(USD_Outflows!$D:$D,USD_Outflows!$A:$A,">="&B4,USD_Outflows!$G:$G,"INR (bought USD)") -> 6536.33
A14: Not claimed: any gain from predicting USD/INR moves. The agent's value is removing avoidable costs (round-trips, deadline-day forced conversions) and timing conversions to actual INR needs.

Sheet Monthly_Summary
A1: Monthly summary (live formulas over the data sheets)
A3: Month | B3: Month end | C3: USD received | D3: INR from conversions (Rs) | E3: INR operating outflows (Rs) | F3: FD sweeps (Rs) | G3: USD costs (USD) | H3: Avoidable FX cost (Rs) | I3: INR balance at month end (Rs) | J3: EEFC USD at month end
A4: 45597 | B4: =MIN(EOMONTH(A4,0),DATE(2026,10,26)) -> 45626 | C4: =SUMIFS(Receipts!$F:$F,Receipts!$I:$I,">="&A4,Receipts!$I:$I,"<="&B4) -> 31630 | D4: =SUMIFS(Conversions!$E:$E,Conversions!$A:$A,">="&A4,Conversions!$A:$A,"<="&B4) -> 2675476.7 | E4: =SUMIFS(INR_Outflows!$D:$D,INR_Outflows!$A:$A,">="&A4,INR_Outflows!$A:$A,"<="&B4,INR_Outflows!$B:$B,"<>Sweep to fixed deposit") -> 3397785 | F4: =SUMIFS(INR_Outflows!$D:$D,INR_Outflows!$A:$A,">="&A4,INR_Outflows!$A:$A,"<="&B4,INR_Outflows!$B:$B,"Sweep to fixed deposit") -> 0 | G4: =SUMIFS(USD_Outflows!$D:$D,USD_Outflows!$A:$A,">="&A4,USD_Outflows!$A:$A,"<="&B4) -> 5036 | H4: =SUMIFS(USD_Outflows!$J:$J,USD_Outflows!$A:$A,">="&A4,USD_Outflows!$A:$A,"<="&B4) -> 12737.74 | I4: =INDEX(Daily_Balances!$B:$B,MATCH(B4,Daily_Balances!$A:$A,0)) -> 6840362.7 | J4: =INDEX(Daily_Balances!$C:$C,MATCH(B4,Daily_Balances!$A:$A,0)) -> 0
A5: 45627 | B5: =MIN(EOMONTH(A5,0),DATE(2026,10,26)) -> 45657 | C5: =SUMIFS(Receipts!$F:$F,Receipts!$I:$I,">="&A5,Receipts!$I:$I,"<="&B5) -> 39770 | D5: =SUMIFS(Conversions!$E:$E,Conversions!$A:$A,">="&A5,Conversions!$A:$A,"<="&B5) -> 3322702.8 | E5: =SUMIFS(INR_Outflows!$D:$D,INR_Outflows!$A:$A,">="&A5,INR_Outflows!$A:$A,"<="&B5,INR_Outflows!$B:$B,"<>Sweep to fixed deposit") -> 3847733 | F5: =SUMIFS(INR_Outflows!$D:$D,INR_Outflows!$A:$A,">="&A5,INR_Outflows!$A:$A,"<="&B5,INR_Outflows!$B:$B,"Sweep to fixed deposit") -> 0 | G5: =SUMIFS(USD_Outflows!$D:$D,USD_Outflows!$A:$A,">="&A5,USD_Outflows!$A:$A,"<="&B5) -> 5158.9 | H5: =SUMIFS(USD_Outflows!$J:$J,USD_Outflows!$A:$A,">="&A5,USD_Outflows!$A:$A,"<="&B5) -> 12923.5 | I5: =INDEX(Daily_Balances!$B:$B,MATCH(B5,Daily_Balances!$A:$A,0)) -> 5871625.6 | J5: =INDEX(Daily_Balances!$C:$C,MATCH(B5,Daily_Balances!$A:$A,0)) -> 0
A6: 45658 | B6: =MIN(EOMONTH(A6,0),DATE(2026,10,26)) -> 45688 | C6: =SUMIFS(Receipts!$F:$F,Receipts!$I:$I,">="&A6,Receipts!$I:$I,"<="&B6) -> 94990 | D6: =SUMIFS(Conversions!$E:$E,Conversions!$A:$A,">="&A6,Conversions!$A:$A,"<="&B6) -> 7945500.6 | E6: =SUMIFS(INR_Outflows!$D:$D,INR_Outflows!$A:$A,">="&A6,INR_Outflows!$A:$A,"<="&B6,INR_Outflows!$B:$B,"<>Sweep to fixed deposit") -> 3380673 | F6: =SUMIFS(INR_Outflows!$D:$D,INR_Outflows!$A:$A,">="&A6,INR_Outflows!$A:$A,"<="&B6,INR_Outflows!$B:$B,"Sweep to fixed deposit") -> 0 | G6: =SUMIFS(USD_Outflows!$D:$D,USD_Outflows!$A:$A,">="&A6,USD_Outflows!$A:$A,"<="&B6) -> 14211 | H6: =SUMIFS(USD_Outflows!$J:$J,USD_Outflows!$A:$A,">="&A6,USD_Outflows!$A:$A,"<="&B6) -> 21042.38 | I6: =INDEX(Daily_Balances!$B:$B,MATCH(B6,Daily_Balances!$A:$A,0)) -> 9227853.3 | J6: =INDEX(Daily_Balances!$C:$C,MATCH(B6,Daily_Balances!$A:$A,0)) -> 0
A7: 45689 | B7: =MIN(EOMONTH(A7,0),DATE(2026,10,26)) -> 45716 | C7: =SUMIFS(Receipts!$F:$F,Receipts!$I:$I,">="&A7,Receipts!$I:$I,"<="&B7) -> 43430 | D7: =SUMIFS(Conversions!$E:$E,Conversions!$A:$A,">="&A7,Conversions!$A:$A,"<="&B7) -> 3668130.8 | E7: =SUMIFS(INR_Outflows!$D:$D,INR_Outflows!$A:$A,">="&A7,INR_Outflows!$A:$A,"<="&B7,INR_Outflows!$B:$B,"<>Sweep to fixed deposit") -> 3348618 | F7: =SUMIFS(INR_Outflows!$D:$D,INR_Outflows!$A:$A,">="&A7,INR_Outflows!$A:$A,"<="&B7,INR_Outflows!$B:$B,"Sweep to fixed deposit") -> 0 | G7: =SUMIFS(USD_Outflows!$D:$D,USD_Outflows!$A:$A,">="&A7,USD_Outflows!$A:$A,"<="&B7) -> 4979.35 | H7: =SUMIFS(USD_Outflows!$J:$J,USD_Outflows!$A:$A,">="&A7,USD_Outflows!$A:$A,"<="&B7) -> 12588.91 | I7: =INDEX(Daily_Balances!$B:$B,MATCH(B7,Daily_Balances!$A:$A,0)) -> 9115147 | J7: =INDEX(Daily_Balances!$C:$C,MATCH(B7,Daily_Balances!$A:$A,0)) -> 0
A8: 45717 | B8: =MIN(EOMONTH(A8,0),DATE(2026,10,26)) -> 45747 | C8: =SUMIFS(Receipts!$F:$F,Receipts!$I:$I,">="&A8,Receipts!$I:$I,"<="&B8) -> 35290 | D8: =SUMIFS(Conversions!$E:$E,Conversions!$A:$A,">="&A8,Conversions!$A:$A,"<="&B8) -> 2987297.1 | E8: =SUMIFS(INR_Outflows!$D:$D,INR_Outflows!$A:$A,">="&A8,INR_Outflows!$A:$A,"<="&B8,INR_Outflows!$B:$B,"<>Sweep to fixed deposit") -> 4261366 | F8: =SUMIFS(INR_Outflows!$D:$D,INR_Outflows!$A:$A,">="&A8,INR_Outflows!$A:$A,"<="&B8,INR_Outflows!$B:$B,"Sweep to fixed deposit") -> 0 | G8: =SUMIFS(USD_Outflows!$D:$D,USD_Outflows!$A:$A,">="&A8,USD_Outflows!$A:$A,"<="&B8) -> 5642.81 | H8: =SUMIFS(USD_Outflows!$J:$J,USD_Outflows!$A:$A,">="&A8,USD_Outflows!$A:$A,"<="&B8) -> 14346.86 | I8: =INDEX(Daily_Balances!$B:$B,MATCH(B8,Daily_Balances!$A:$A,0)) -> 7348502.5 | J8: =INDEX(Daily_Balances!$C:$C,MATCH(B8,Daily_Balances!$A:$A,0)) -> 0
A9: 45748 | B9: =MIN(EOMONTH(A9,0),DATE(2026,10,26)) -> 45777 | C9: =SUMIFS(Receipts!$F:$F,Receipts!$I:$I,">="&A9,Receipts!$I:$I,"<="&B9) -> 51570 | D9: =SUMIFS(Conversions!$E:$E,Conversions!$A:$A,">="&A9,Conversions!$A:$A,"<="&B9) -> 4386653.4 | E9: =SUMIFS(INR_Outflows!$D:$D,INR_Outflows!$A:$A,">="&A9,INR_Outflows!$A:$A,"<="&B9,INR_Outflows!$B:$B,"<>Sweep to fixed deposit") -> 3738645 | F9: =SUMIFS(INR_Outflows!$D:$D,INR_Outflows!$A:$A,">="&A9,INR_Outflows!$A:$A,"<="&B9,INR_Outflows!$B:$B,"Sweep to fixed deposit") -> 0 | G9: =SUMIFS(USD_Outflows!$D:$D,USD_Outflows!$A:$A,">="&A9,USD_Outflows!$A:$A,"<="&B9) -> 14318.76 | H9: =SUMIFS(USD_Outflows!$J:$J,USD_Outflows!$A:$A,">="&A9,USD_Outflows!$A:$A,"<="&B9) -> 21700.57 | I9: =INDEX(Daily_Balances!$B:$B,MATCH(B9,Daily_Balances!$A:$A,0)) -> 6755776.6 | J9: =INDEX(Daily_Balances!$C:$C,MATCH(B9,Daily_Balances!$A:$A,0)) -> 0
A10: 45778 | B10: =MIN(EOMONTH(A10,0),DATE(2026,10,26)) -> 45808 | C10: =SUMIFS(Receipts!$F:$F,Receipts!$I:$I,">="&A10,Receipts!$I:$I,"<="&B10) -> 43430 | D10: =SUMIFS(Conversions!$E:$E,Conversions!$A:$A,">="&A10,Conversions!$A:$A,"<="&B10) -> 3687022.2 | E10: =SUMIFS(INR_Outflows!$D:$D,INR_Outflows!$A:$A,">="&A10,INR_Outflows!$A:$A,"<="&B10,INR_Outflows!$B:$B,"<>Sweep to fixed deposit") -> 3705387 | F10: =SUMIFS(INR_Outflows!$D:$D,INR_Outflows!$A:$A,">="&A10,INR_Outflows!$A:$A,"<="&B10,INR_Outflows!$B:$B,"Sweep to fixed deposit") -> 0 | G10: =SUMIFS(USD_Outflows!$D:$D,USD_Outflows!$A:$A,">="&A10,USD_Outflows!$A:$A,"<="&B10) -> 5566.46 | H10: =SUMIFS(USD_Outflows!$J:$J,USD_Outflows!$A:$A,">="&A10,USD_Outflows!$A:$A,"<="&B10) -> 14272.98 | I10: =INDEX(Daily_Balances!$B:$B,MATCH(B10,Daily_Balances!$A:$A,0)) -> 6247372.6 | J10: =INDEX(Daily_Balances!$C:$C,MATCH(B10,Daily_Balances!$A:$A,0)) -> 0
A11: 45809 | B11: =MIN(EOMONTH(A11,0),DATE(2026,10,26)) -> 45838 | C11: =SUMIFS(Receipts!$F:$F,Receipts!$I:$I,">="&A11,Receipts!$I:$I,"<="&B11) -> 46500 | D11: =SUMIFS(Conversions!$E:$E,Conversions!$A:$A,">="&A11,Conversions!$A:$A,"<="&B11) -> 3995479.6 | E11: =SUMIFS(INR_Outflows!$D:$D,INR_Outflows!$A:$A,">="&A11,INR_Outflows!$A:$A,"<="&B11,INR_Outflows!$B:$B,"<>Sweep to fixed deposit") -> 3957885 | F11: =SUMIFS(INR_Outflows!$D:$D,INR_Outflows!$A:$A,">="&A11,INR_Outflows!$A:$A,"<="&B11,INR_Outflows!$B:$B,"Sweep to fixed deposit") -> 0 | G11: =SUMIFS(USD_Outflows!$D:$D,USD_Outflows!$A:$A,">="&A11,USD_Outflows!$A:$A,"<="&B11) -> 5647.66 | H11: =SUMIFS(USD_Outflows!$J:$J,USD_Outflows!$A:$A,">="&A11,USD_Outflows!$A:$A,"<="&B11) -> 14540.29 | I11: =INDEX(Daily_Balances!$B:$B,MATCH(B11,Daily_Balances!$A:$A,0)) -> 5785750.6 | J11: =INDEX(Daily_Balances!$C:$C,MATCH(B11,Daily_Balances!$A:$A,0)) -> 0
A12: 45839 | B12: =MIN(EOMONTH(A12,0),DATE(2026,10,26)) -> 45869 | C12: =SUMIFS(Receipts!$F:$F,Receipts!$I:$I,">="&A12,Receipts!$I:$I,"<="&B12) -> 87210 | D12: =SUMIFS(Conversions!$E:$E,Conversions!$A:$A,">="&A12,Conversions!$A:$A,"<="&B12) -> 7444930.4 | E12: =SUMIFS(INR_Outflows!$D:$D,INR_Outflows!$A:$A,">="&A12,INR_Outflows!$A:$A,"<="&B12,INR_Outflows!$B:$B,"<>Sweep to fixed deposit") -> 3656161 | F12: =SUMIFS(INR_Outflows!$D:$D,INR_Outflows!$A:$A,">="&A12,INR_Outflows!$A:$A,"<="&B12,INR_Outflows!$B:$B,"Sweep to fixed deposit") -> 0 | G12: =SUMIFS(USD_Outflows!$D:$D,USD_Outflows!$A:$A,">="&A12,USD_Outflows!$A:$A,"<="&B12) -> 14766.49 | H12: =SUMIFS(USD_Outflows!$J:$J,USD_Outflows!$A:$A,">="&A12,USD_Outflows!$A:$A,"<="&B12) -> 22968.32 | I12: =INDEX(Daily_Balances!$B:$B,MATCH(B12,Daily_Balances!$A:$A,0)) -> 8287044.2 | J12: =INDEX(Daily_Balances!$C:$C,MATCH(B12,Daily_Balances!$A:$A,0)) -> 0
A13: 45870 | B13: =MIN(EOMONTH(A13,0),DATE(2026,10,26)) -> 45900 | C13: =SUMIFS(Receipts!$F:$F,Receipts!$I:$I,">="&A13,Receipts!$I:$I,"<="&B13) -> 46500 | D13: =SUMIFS(Conversions!$E:$E,Conversions!$A:$A,">="&A13,Conversions!$A:$A,"<="&B13) -> 3979780.5 | E13: =SUMIFS(INR_Outflows!$D:$D,INR_Outflows!$A:$A,">="&A13,INR_Outflows!$A:$A,"<="&B13,INR_Outflows!$B:$B,"<>Sweep to fixed deposit") -> 3789873 | F13: =SUMIFS(INR_Outflows!$D:$D,INR_Outflows!$A:$A,">="&A13,INR_Outflows!$A:$A,"<="&B13,INR_Outflows!$B:$B,"Sweep to fixed deposit") -> 0 | G13: =SUMIFS(USD_Outflows!$D:$D,USD_Outflows!$A:$A,">="&A13,USD_Outflows!$A:$A,"<="&B13) -> 5741 | H13: =SUMIFS(USD_Outflows!$J:$J,USD_Outflows!$A:$A,">="&A13,USD_Outflows!$A:$A,"<="&B13) -> 14686.63 | I13: =INDEX(Daily_Balances!$B:$B,MATCH(B13,Daily_Balances!$A:$A,0)) -> 7972710.8 | J13: =INDEX(Daily_Balances!$C:$C,MATCH(B13,Daily_Balances!$A:$A,0)) -> 0
A14: 45901 | B14: =MIN(EOMONTH(A14,0),DATE(2026,10,26)) -> 45930 | C14: =SUMIFS(Receipts!$F:$F,Receipts!$I:$I,">="&A14,Receipts!$I:$I,"<="&B14) -> 52640 | D14: =SUMIFS(Conversions!$E:$E,Conversions!$A:$A,">="&A14,Conversions!$A:$A,"<="&B14) -> 4468363 | E14: =SUMIFS(INR_Outflows!$D:$D,INR_Outflows!$A:$A,">="&A14,INR_Outflows!$A:$A,"<="&B14,INR_Outflows!$B:$B,"<>Sweep to fixed deposit") -> 4371224 | F14: =SUMIFS(INR_Outflows!$D:$D,INR_Outflows!$A:$A,">="&A14,INR_Outflows!$A:$A,"<="&B14,INR_Outflows!$B:$B,"Sweep to fixed deposit") -> 0 | G14: =SUMIFS(USD_Outflows!$D:$D,USD_Outflows!$A:$A,">="&A14,USD_Outflows!$A:$A,"<="&B14) -> 5486.77 | H14: =SUMIFS(USD_Outflows!$J:$J,USD_Outflows!$A:$A,">="&A14,USD_Outflows!$A:$A,"<="&B14) -> 13991.46 | I14: =INDEX(Daily_Balances!$B:$B,MATCH(B14,Daily_Balances!$A:$A,0)) -> 7589476.2 | J14: =INDEX(Daily_Balances!$C:$C,MATCH(B14,Daily_Balances!$A:$A,0)) -> 0
A15: 45931 | B15: =MIN(EOMONTH(A15,0),DATE(2026,10,26)) -> 45961 | C15: =SUMIFS(Receipts!$F:$F,Receipts!$I:$I,">="&A15,Receipts!$I:$I,"<="&B15) -> 52640 | D15: =SUMIFS(Conversions!$E:$E,Conversions!$A:$A,">="&A15,Conversions!$A:$A,"<="&B15) -> 4498823.4 | E15: =SUMIFS(INR_Outflows!$D:$D,INR_Outflows!$A:$A,">="&A15,INR_Outflows!$A:$A,"<="&B15,INR_Outflows!$B:$B,"<>Sweep to fixed deposit") -> 3718270 | F15: =SUMIFS(INR_Outflows!$D:$D,INR_Outflows!$A:$A,">="&A15,INR_Outflows!$A:$A,"<="&B15,INR_Outflows!$B:$B,"Sweep to fixed deposit") -> 0 | G15: =SUMIFS(USD_Outflows!$D:$D,USD_Outflows!$A:$A,">="&A15,USD_Outflows!$A:$A,"<="&B15) -> 14674.41 | H15: =SUMIFS(USD_Outflows!$J:$J,USD_Outflows!$A:$A,">="&A15,USD_Outflows!$A:$A,"<="&B15) -> 22552.44 | I15: =INDEX(Daily_Balances!$B:$B,MATCH(B15,Daily_Balances!$A:$A,0)) -> 7098205 | J15: =INDEX(Daily_Balances!$C:$C,MATCH(B15,Daily_Balances!$A:$A,0)) -> 0
... A27: 46296 | B27: =MIN(EOMONTH(A27,0),DATE(2026,10,26)) -> 46321 | C27: =SUMIFS(Receipts!$F:$F,Receipts!$I:$I,">="&A27,Receipts!$I:$I,"<="&B27) -> 71190 | D27: =SUMIFS(Conversions!$E:$E,Conversions!$A:$A,">="&A27,Conversions!$A:$A,"<="&B27) -> 0 | E27: =SUMIFS(INR_Outflows!$D:$D,INR_Outflows!$A:$A,">="&A27,INR_Outflows!$A:$A,"<="&B27,INR_Outflows!$B:$B,"<>Sweep to fixed deposit") -> 4169077 | F27: =SUMIFS(INR_Outflows!$D:$D,INR_Outflows!$A:$A,">="&A27,INR_Outflows!$A:$A,"<="&B27,INR_Outflows!$B:$B,"Sweep to fixed deposit") -> 0 | G27: =SUMIFS(USD_Outflows!$D:$D,USD_Outflows!$A:$A,">="&A27,USD_Outflows!$A:$A,"<="&B27) -> 17567.58 | H27: =SUMIFS(USD_Outflows!$J:$J,USD_Outflows!$A:$A,">="&A27,USD_Outflows!$A:$A,"<="&B27) -> 0 | I27: =INDEX(Daily_Balances!$B:$B,MATCH(B27,Daily_Balances!$A:$A,0)) -> 856292.58 | J27: =INDEX(Daily_Balances!$C:$C,MATCH(B27,Daily_Balances!$A:$A,0)) -> 92522.42
A28: Total | C28: =SUM(C4:C27) -> 1427000 | D28: =SUM(D4:D27) -> 1.1330017e+08 | E28: =SUM(E4:E27) -> 95039252 | F28: =SUM(F4:F27) -> 7900000 | G28: =SUM(G4:G27) -> 217508.24 | H28: =SUM(H4:H27) -> 407683.5

Sheet Detected_Patterns
A1: Obligation | B1: Ccy | C1: Cadence | D1: Times seen | E1: Last seen | F1: Next expected | G1: Estimate | H1: Range low | I1: Range high | J1: Confidence % | K1: Band | L1: History factor | M1: Timing factor | N1: Amount factor | O1: Trend break? | P1: Agent note
A2: Payroll | B2: INR | C2: Monthly | D2: 24 | E2: 46296 | F2: 46328 | G2: 3709600 | H2: 3635408 | I2: 3783792 | J2: 93 | K2: High | L2: 1 | M2: 0.95 | N2: 0.98 | O2: =FALSE() -> FALSE | P2: Salary run on the 1st (next business day if weekend); steps up each April appraisal + Aug 2026 hires
A3: Rent | B3: INR | C3: Monthly | D3: 24 | E3: 46300 | F3: 46331 | G3: 336000 | H3: 329280 | I3: 342720 | J3: 95 | K3: High | L3: 1 | M3: 0.95 | N3: 1 | O3: =FALSE() -> FALSE | P3: Fixed amount, 5% escalation each April
A4: GST | B4: INR | C4: Monthly | D4: 24 | E4: 46315 | F4: 46346 | G4: 171812 | H4: 123477 | I4: 229703 | J4: 59 | K4: Medium | L4: 1 | M4: 0.95 | N4: 0.61 | O4: =TRUE() -> TRUE | P4: Paid on the 20th; amount varies month to month
A5: Advance tax | B5: INR | C5: Quarterly | D5: 8 | E5: 46280 | F5: 46371 | G5: 600000 | H5: 550000 | I5: 700000 | J5: 52 | K5: Medium | L5: 0.96 | M5: 0.95 | N5: 0.57 | O5: =TRUE() -> TRUE | P5: Quarterly on 15 Jun/Sep/Dec/Mar; next is outside the 30-day window
A6: Team offsite (Coorg Retreats) | B6: INR | C6: Unknown (seen once) | D6: 1 | E6: 45975 | F6: 46339 | G6: 420000 | H6: 0 | I6: 450000 | J6: 17 | K6: Low | L6: 0.58 | M6: 0.6 | N6: 0.5 | O6: =FALSE() -> FALSE | P6: Paid once in Nov 2025 - agent cannot tell if it recurs; asks the merchant
A7: AWS | B7: USD | C7: Monthly | D7: 24 | E7: 46300 | F7: 46329 | G7: 7277.58 | H7: 6185.94 | I7: 8369.22 | J7: 67 | K7: Medium | L7: 1 | M7: 0.95 | N7: 0.7 | O7: =TRUE() -> TRUE | P7: Billed on the 3rd; usage spiked +18% in Sep and +31% in Oct (Atlas onboarding)
A8: Dev & collaboration tools | B8: USD | C8: Monthly | D8: 24 | E8: 46302 | F8: 46335 | G8: 1290 | H8: 1290 | I8: 1290 | J8: 95 | K8: High | L8: 1 | M8: 0.95 | N8: 1 | O8: =FALSE() -> FALSE | P8: Fixed seat-based plan
A9: Marisol Vega Design LLC (US) | B9: USD | C9: Quarterly | D9: 8 | E9: 46307 | F9: 46398 | G9: 9000 | H9: 9000 | I9: 9000 | J9: 90 | K9: High | L9: 0.96 | M9: 0.94 | N9: 1 | O9: =FALSE() -> FALSE | P9: Quarterly wire on the 10th; next is outside the window
A11: Confidence = 100 x history factor x timing factor x amount factor. History = sqrt(min(1,(n+3)/12)); timing = 1 - min(0.4, sd of day/15) (0.6 if seen once); amount = 1 - min(0.5, CV of last 6), x0.8 if the latest value breaks >10% from the prior average. Illustrative heuristic for the prototype.

Sheet Client_Behaviour
A1: ID | B1: Client | C1: Plan | D1: Status | E1: Invoices paid | F1: Avg days after due (- = early) | G1: SD (days) | H1: Latest invoice (USD) | I1: Timing confidence % | J1: Band
A2: C01 | B2: Harborline Logistics | C2: Monthly | D2: Active | E2: 24 | F2: -4.7 | G2: 2.8 | H2: 7760 | I2: 89 | J2: High
A3: C02 | B3: Brightpath Health | C3: Monthly | D3: Active | E3: 23 | F3: 34 | G3: 7.1 | H3: 8630 | I3: 72 | J3: Medium
A4: C03 | B4: Cedar & Finch Retail | C4: Monthly | D4: Churned (last invoice Mar 2026) | E4: 17 | F4: -4.4 | G4: 2.9 | H4: 5130 | I4: 86 | J4: High
A5: C04 | B5: Northgate Insurance Group | C5: Annual | D5: Annual payer | E5: 2 | F5: 4.5 | G5: 0.5 | H5: 55220 | I5: 63 | J5: Medium
A6: C05 | B6: Bluefjord Media | C6: Annual | D6: Annual payer | E6: 2 | F6: 1 | G6: 4 | H6: 40710 | I6: 54 | J6: Medium
A7: C06 | B7: Quillmark Legal | C7: Monthly | D7: Active | E7: 24 | F7: -6.2 | G7: 2.9 | H7: 4630 | I7: 89 | J7: High
A8: C07 | B8: Solace Fitness | C8: Monthly | D8: Active | E8: 21 | F8: -5.4 | G8: 3.4 | H8: 3880 | I8: 86 | J8: High
A9: C08 | B9: Tidewater Credit Union | C9: Monthly | D9: Active | E9: 24 | F9: -5.3 | G9: 2.5 | H9: 9250 | I9: 90 | J9: High
A10: C09 | B10: Ember Labs | C10: Monthly | D10: Active | E10: 17 | F10: -5.6 | G10: 3.1 | H10: 3250 | I10: 87 | J10: High
A11: C10 | B11: Pinecrest Schools | C11: Monthly | D11: Active | E11: 14 | F11: -4.9 | G11: 2.4 | H11: 6510 | I11: 90 | J11: High
A12: C11 | B12: Atlas Freight Partners | C12: Monthly | D12: Active | E12: 3 | F12: 4.3 | G12: 1.2 | H12: 17110 | I12: 67 | J12: Medium
A13: C12 | B13: Kestrel Analytics | C13: Monthly | D13: Active | E13: 24 | F13: -6 | G13: 2.5 | H13: 6750 | I13: 90 | J13: High
A14: C13 | B14: Orchard Robotics | C14: Monthly | D14: Active | E14: 8 | F14: -4.1 | G14: 2 | H14: 3420 | I14: 88 | J14: High

Sheet Receipts
A1: Invoice ID | B1: Client ID | C1: Client | D1: Plan | E1: Currency | F1: Amount (USD) | G1: Invoice date | H1: Due date | I1: Paid date | J1: Days after due | K1: Status
A2: INV-202411-C01 | B2: C01 | C2: Harborline Logistics | D2: Monthly | E2: USD | F2: 7320 | G2: 45597 | H2: 45612 | I2: 45607 | J2: -5 | K2: Paid
A3: INV-202411-C02 | B3: C02 | C3: Brightpath Health | D3: Monthly | E3: USD | F3: 8140 | G3: 45597 | H3: 45612 | I3: 45636 | J3: 24 | K3: Paid
A4: INV-202411-C03 | B4: C03 | C4: Cedar & Finch Retail | D4: Monthly | E4: USD | F4: 4840 | G4: 45597 | H4: 45612 | I4: 45607 | J4: -5 | K4: Paid
A5: INV-202411-C06 | B5: C06 | C5: Quillmark Legal | D5: Monthly | E5: USD | F5: 4370 | G5: 45597 | H5: 45612 | I5: 45607 | J5: -5 | K5: Paid
A6: INV-202411-C08 | B6: C08 | C6: Tidewater Credit Union | D6: Monthly | E6: USD | F6: 8730 | G6: 45597 | H6: 45612 | I6: 45609 | J6: -3 | K6: Paid
A7: INV-202411-C12 | B7: C12 | C7: Kestrel Analytics | D7: Monthly | E7: USD | F7: 6370 | G7: 45597 | H7: 45612 | I7: 45607 | J7: -5 | K7: Paid
A8: INV-202412-C01 | B8: C01 | C8: Harborline Logistics | D8: Monthly | E8: USD | F8: 7320 | G8: 45628 | H8: 45643 | I8: 45642 | J8: -1 | K8: Paid
A9: INV-202412-C02 | B9: C02 | C9: Brightpath Health | D9: Monthly | E9: USD | F9: 8140 | G9: 45628 | H9: 45643 | I9: 45677 | J9: 34 | K9: Paid
A10: INV-202412-C03 | B10: C03 | C10: Cedar & Finch Retail | D10: Monthly | E10: USD | F10: 4840 | G10: 45628 | H10: 45643 | I10: 45635 | J10: -8 | K10: Paid
A11: INV-202412-C06 | B11: C06 | C11: Quillmark Legal | D11: Monthly | E11: USD | F11: 4370 | G11: 45628 | H11: 45643 | I11: 45639 | J11: -4 | K11: Paid
A12: INV-202412-C08 | B12: C08 | C12: Tidewater Credit Union | D12: Monthly | E12: USD | F12: 8730 | G12: 45628 | H12: 45643 | I12: 45635 | J12: -8 | K12: Paid
A13: INV-202412-C12 | B13: C12 | C13: Kestrel Analytics | D13: Monthly | E13: USD | F13: 6370 | G13: 45628 | H13: 45643 | I13: 45635 | J13: -8 | K13: Paid
... A196: INV-202610-C01 | B196: C01 | C196: Harborline Logistics | D196: Monthly | E196: USD | F196: 7760 | G196: 46296 | H196: 46311 | I196: 46309 | J196: -2 | K196: Paid
A197: INV-202610-C02 | B197: C02 | C197: Brightpath Health | D197: Monthly | E197: USD | F197: 8630 | G197: 46296 | H197: 46311 | K197: Outstanding
A198: INV-202610-C06 | B198: C06 | C198: Quillmark Legal | D198: Monthly | E198: USD | F198: 4630 | G198: 46296 | H198: 46311 | I198: 46303 | J198: -8 | K198: Paid
A199: INV-202610-C07 | B199: C07 | C199: Solace Fitness | D199: Monthly | E199: USD | F199: 3880 | G199: 46296 | H199: 46311 | I199: 46302 | J199: -9 | K199: Paid
A200: INV-202610-C08 | B200: C08 | C200: Tidewater Credit Union | D200: Monthly | E200: USD | F200: 9250 | G200: 46296 | H200: 46311 | I200: 46307 | J200: -4 | K200: Paid
A201: INV-202610-C09 | B201: C09 | C201: Ember Labs | D201: Monthly | E201: USD | F201: 3250 | G201: 46296 | H201: 46311 | I201: 46307 | J201: -4 | K201: Paid
A202: INV-202610-C10 | B202: C10 | C202: Pinecrest Schools | D202: Monthly | E202: USD | F202: 6510 | G202: 46296 | H202: 46311 | I202: 46307 | J202: -4 | K202: Paid
A203: INV-202610-C11 | B203: C11 | C203: Atlas Freight Partners | D203: Monthly | E203: USD | F203: 17110 | G203: 46296 | H203: 46311 | I203: 46315 | J203: 4 | K203: Paid
A204: INV-202610-C12 | B204: C12 | C204: Kestrel Analytics | D204: Monthly | E204: USD | F204: 6750 | G204: 46296 | H204: 46311 | I204: 46302 | J204: -9 | K204: Paid
A205: INV-202610-C13 | B205: C13 | C205: Orchard Robotics | D205: Monthly | E205: USD | F205: 3420 | G205: 46296 | H205: 46311 | I205: 46304 | J205: -7 | K205: Paid
A206: INV-202611-C01 | B206: C01 | C206: Harborline Logistics | D206: Monthly | E206: USD | F206: 7760 | G206: 46328 | H206: 46343 | K206: Scheduled (not yet invoiced)
A207: INV-202611-C02 | B207: C02 | C207: Brightpath Health | D207: Monthly | E207: USD | F207: 8630 | G207: 46328 | H207: 46343 | K207: Scheduled (not yet invoiced)
A208: INV-202611-C06 | B208: C06 | C208: Quillmark Legal | D208: Monthly | E208: USD | F208: 4630 | G208: 46328 | H208: 46343 | K208: Scheduled (not yet invoiced)
A209: INV-202611-C07 | B209: C07 | C209: Solace Fitness | D209: Monthly | E209: USD | F209: 3880 | G209: 46328 | H209: 46343 | K209: Scheduled (not yet invoiced)
A210: INV-202611-C08 | B210: C08 | C210: Tidewater Credit Union | D210: Monthly | E210: USD | F210: 9250 | G210: 46328 | H210: 46343 | K210: Scheduled (not yet invoiced)
A211: INV-202611-C09 | B211: C09 | C211: Ember Labs | D211: Monthly | E211: USD | F211: 3250 | G211: 46328 | H211: 46343 | K211: Scheduled (not yet invoiced)
A212: INV-202611-C10 | B212: C10 | C212: Pinecrest Schools | D212: Monthly | E212: USD | F212: 6510 | G212: 46328 | H212: 46343 | K212: Scheduled (not yet invoiced)
A213: INV-202611-C11 | B213: C11 | C213: Atlas Freight Partners | D213: Monthly | E213: USD | F213: 17110 | G213: 46328 | H213: 46343 | K213: Scheduled (not yet invoiced)
A214: INV-202611-C12 | B214: C12 | C214: Kestrel Analytics | D214: Monthly | E214: USD | F214: 6750 | G214: 46328 | H214: 46343 | K214: Scheduled (not yet invoiced)
A215: INV-202611-C13 | B215: C13 | C215: Orchard Robotics | D215: Monthly | E215: USD | F215: 3420 | G215: 46328 | H215: 46343 | K215: Scheduled (not yet invoiced)
A216: INV-202612-C01 | B216: C01 | C216: Harborline Logistics | D216: Monthly | E216: USD | F216: 7760 | G216: 46357 | H216: 46372 | K216: Scheduled (not yet invoiced)
A217: INV-202612-C02 | B217: C02 | C217: Brightpath Health | D217: Monthly | E217: USD | F217: 8630 | G217: 46357 | H217: 46372 | K217: Scheduled (not yet invoiced)
... A225: INV-202612-C13 | B225: C13 | C225: Orchard Robotics | D225: Monthly | E225: USD | F225: 3420 | G225: 46357 | H225: 46372 | K225: Scheduled (not yet invoiced)

Sheet INR_Outflows
A1: Date | B1: Category | C1: Payee | D1: Amount (Rs) | E1: Recurring?
A2: 45597 | B2: Payroll | C2: Employees (salary run) | D2: 2845729 | E2: Monthly
A3: 45601 | B3: Rent | C3: Prestige Workspace LLP | D3: 320000 | E3: Monthly
A4: 45616 | B4: GST | C4: GSTN (domestic sales + RCM) | D4: 232056 | E4: Monthly
A5: 45628 | B5: Payroll | C5: Employees (salary run) | D5: 2842527 | E5: Monthly
A6: 45631 | B6: Rent | C6: Prestige Workspace LLP | D6: 320000 | E6: Monthly
A7: 45642 | B7: Advance tax | C7: Income Tax Dept | D7: 550000 | E7: Quarterly
A8: 45646 | B8: GST | C8: GSTN (domestic sales + RCM) | D8: 135206 | E8: Monthly
A9: 45658 | B9: Payroll | C9: Employees (salary run) | D9: 2875831 | E9: Monthly
A10: 45663 | B10: Rent | C10: Prestige Workspace LLP | D10: 320000 | E10: Monthly
A11: 45677 | B11: GST | C11: GSTN (domestic sales + RCM) | D11: 184842 | E11: Monthly
A12: 45691 | B12: Payroll | C12: Employees (salary run) | D12: 2866679 | E12: Monthly
A13: 45693 | B13: Rent | C13: Prestige Workspace LLP | D13: 320000 | E13: Monthly
... A89: 46315 | B89: GST | C89: GSTN (domestic sales + RCM) | D89: 123477 | E89: Monthly

Sheet USD_Outflows
A1: Date | B1: Category | C1: Payee | D1: Amount (USD) | E1: Channel | F1: Recurring? | G1: Paid from | H1: Mid rate | I1: INR cost (Rs) | J1: Avoidable FX cost (Rs)
A2: 45600 | B2: Cloud hosting | C2: AWS | D2: 3886 | E2: Corporate card | F2: Monthly | G2: INR (bought USD) | H2: 84.2228 | I2: 337108.49 | J2: 9818.69
A3: 45603 | B3: SaaS tools | C3: Dev & collaboration tools | D3: 1150 | E3: Corporate card | F3: Monthly | G3: INR (bought USD) | H3: 84.61 | I3: 100220.54 | J3: 2919.05
A4: 45629 | B4: Cloud hosting | C4: AWS | D4: 4008.9 | E4: Corporate card | F4: Monthly | G4: INR (bought USD) | H4: 83.4963 | I4: 344770.17 | J4: 10041.85
A5: 45635 | B5: SaaS tools | C5: Dev & collaboration tools | D5: 1150 | E5: Corporate card | F5: Monthly | G5: INR (bought USD) | H5: 83.5262 | I5: 98936.78 | J5: 2881.65
A6: 45660 | B6: Cloud hosting | C6: AWS | D6: 4061 | E6: Corporate card | F6: Monthly | G6: INR (bought USD) | H6: 83.668 | I6: 349969.02 | J6: 10193.27
A7: 45664 | B7: SaaS tools | C7: Dev & collaboration tools | D7: 1150 | E7: Corporate card | F7: Monthly | G7: INR (bought USD) | H7: 83.6058 | I7: 99031.07 | J7: 2884.4
A8: 45667 | B8: Contractor | C8: Marisol Vega Design LLC (US) | D8: 9000 | E8: Bank wire | F8: Quarterly | G8: INR (bought USD) | H8: 83.515 | I8: 759599.71 | J8: 7964.71
A9: 45691 | B9: Cloud hosting | C9: AWS | D9: 3829.35 | E9: Corporate card | F9: Monthly | G9: INR (bought USD) | H9: 84.2082 | I9: 332136.55 | J9: 9673.88
A10: 45695 | B10: SaaS tools | C10: Dev & collaboration tools | D10: 1150 | E10: Corporate card | F10: Monthly | G10: INR (bought USD) | H10: 84.4935 | I10: 100082.55 | J10: 2915.03
A11: 45719 | B11: Cloud hosting | C11: AWS | D11: 4492.81 | E11: Corporate card | F11: Monthly | G11: INR (bought USD) | H11: 84.7501 | I11: 392189.08 | J11: 11422.98
A12: 45723 | B12: SaaS tools | C12: Dev & collaboration tools | D12: 1150 | E12: Corporate card | F12: Monthly | G12: INR (bought USD) | H12: 84.7501 | I12: 100386.49 | J12: 2923.88
A13: 45750 | B13: Cloud hosting | C13: AWS | D13: 4168.76 | E13: Corporate card | F13: Monthly | G13: INR (bought USD) | H13: 85.3718 | I13: 366571.38 | J13: 10676.84
... A57: 46307 | B57: Contractor | C57: Marisol Vega Design LLC (US) | D57: 9000 | E57: Bank wire | F57: Quarterly | G57: EEFC (USD) | H57: 87.9507 | I57: 0 | J57: 0

Sheet Conversions
A1: Date | B1: Type | C1: USD | D1: Rate | E1: INR (Rs) | F1: Source | G1: From EEFC bucket
A2: 45607 | B2: Auto at settlement | C2: 7320 | D2: 84.5224 | E2: 618703.97 | F2: INV-202411-C01
A3: 45607 | B3: Auto at settlement | C3: 4840 | D3: 84.5224 | E3: 409088.42 | F3: INV-202411-C03
A4: 45607 | B4: Auto at settlement | C4: 4370 | D4: 84.5224 | E4: 369362.89 | F4: INV-202411-C06
A5: 45607 | B5: Auto at settlement | C5: 6370 | D5: 84.5224 | E5: 538407.69 | F5: INV-202411-C12
A6: 45609 | B6: Auto at settlement | C6: 8730 | D6: 84.7553 | E6: 739913.77 | F6: INV-202411-C08
A7: 45635 | B7: Auto at settlement | C7: 4840 | D7: 83.5262 | E7: 404266.81 | F7: INV-202412-C03
A8: 45635 | B8: Auto at settlement | C8: 8730 | D8: 83.5262 | E8: 729183.73 | F8: INV-202412-C08
A9: 45635 | B9: Auto at settlement | C9: 6370 | D9: 83.5262 | E9: 532061.89 | F9: INV-202412-C12
A10: 45636 | B10: Auto at settlement | C10: 8140 | D10: 83.4755 | E10: 679490.57 | F10: INV-202411-C02
A11: 45639 | B11: Auto at settlement | C11: 4370 | D11: 83.7238 | E11: 365873.01 | F11: INV-202412-C06
A12: 45642 | B12: Auto at settlement | C12: 7320 | D12: 83.5829 | E12: 611826.83 | F12: INV-202412-C01
A13: 45664 | B13: Auto at settlement | C13: 4370 | D13: 83.6058 | E13: 365357.35 | F13: INV-202501-C06
... A184: 46262 | B184: Auto at settlement | C184: 8630 | D184: 88.0351 | E184: 759742.91 | F184: INV-202607-C02
A185: 46294 | B185: Manual - fund Oct payroll, rent & GST | C185: 31000 | D185: 87.5586 | E185: 2714316.6 | F185: EEFC | G185: 2026-09

Sheet EEFC_Ledger
A1: Date | B1: Entry | C1: Reference | D1: USD (+credit / -debit) | E1: Bucket (month received)
A2: 46272 | B2: Credit - receipt | C2: INV-202609-C06 | D2: 4630 | E2: 2026-09
A3: 46272 | B3: Credit - receipt | C3: INV-202609-C10 | D3: 6510 | E3: 2026-09
A4: 46272 | B4: Debit - paid Dev & collaboration tools | C4: SaaS tools | D4: -1290 | E4: 2026-09
A5: 46273 | B5: Credit - receipt | C5: INV-202609-C08 | D5: 9250 | E5: 2026-09
A6: 46279 | B6: Credit - receipt | C6: INV-202609-C01 | D6: 7760 | E6: 2026-09
A7: 46279 | B7: Credit - receipt | C7: INV-202609-C12 | D7: 6750 | E7: 2026-09
A8: 46279 | B8: Credit - receipt | C8: INV-202609-C13 | D8: 3420 | E8: 2026-09
A9: 46280 | B9: Credit - receipt | C9: INV-202609-C07 | D9: 3880 | E9: 2026-09
A10: 46280 | B10: Credit - receipt | C10: INV-202609-C09 | D10: 3250 | E10: 2026-09
A11: 46286 | B11: Credit - receipt | C11: INV-202608-C02 | D11: 8630 | E11: 2026-09
A12: 46287 | B12: Credit - receipt | C12: INV-202609-C11 | D12: 17110 | E12: 2026-09
A13: 46294 | B13: Debit - conversion to INR | C13: Manual - fund Oct payroll, rent & GST | D13: -31000 | E13: 2026-09
... A26: 46315 | B26: Credit - receipt | C26: INV-202610-C11 | D26: 17110 | E26: 2026-10

Sheet Daily_Balances
A1: Date | B1: INR balance (Rs) | C1: EEFC balance (USD)
A2: 45597 | B2: 5154271 | C2: 0
A3: 45598 | B3: 5154271 | C3: 0
A4: 45599 | B4: 5154271 | C4: 0
A5: 45600 | B5: 4817162.5 | C5: 0
A6: 45601 | B6: 4497162.5 | C6: 0
A7: 45602 | B7: 4497162.5 | C7: 0
A8: 45603 | B8: 4396942 | C8: 0
A9: 45604 | B9: 4396942 | C9: 0
A10: 45605 | B10: 4396942 | C10: 0
A11: 45606 | B11: 4396942 | C11: 0
A12: 45607 | B12: 6332504.9 | C12: 0
A13: 45608 | B13: 6332504.9 | C13: 0
... A726: 46321 | B726: 856292.58 | C726: 92522.42

Sheet FX_Rates
A1: Date | B1: USD/INR mid (synthetic)
A2: 45597 | B2: 84.5482
A3: 45600 | B3: 84.2228
A4: 45601 | B4: 84.5024
A5: 45602 | B5: 84.4872
A6: 45603 | B6: 84.61
A7: 45604 | B7: 84.5878
A8: 45607 | B8: 84.5224
A9: 45608 | B9: 84.6067
A10: 45609 | B10: 84.7553
A11: 45610 | B11: 84.7213
A12: 45611 | B12: 84.6961
A13: 45614 | B13: 84.8201
... A518: 46321 | B518: 88.42

Sheet Clients
A1: ID | B1: Client | C1: Country | D1: Plan | E1: Price at start (USD) | F1: Start | G1: End | H1: Behaviour
A2: C01 | B2: Harborline Logistics | C2: US | D2: Monthly | E2: 7320 | F2: 2024-11 | H2: Pays on time
A3: C02 | B3: Brightpath Health | C3: US | D3: Monthly | E3: 8140 | F3: 2024-11 | H3: Late payer (30-45 days past due)
A4: C03 | B4: Cedar & Finch Retail | C4: US | D4: Monthly | E4: 4840 | F4: 2024-11 | G4: 2026-03 | H4: Pays on time
A5: C04 | B5: Northgate Insurance Group | C5: US | D5: Annual | E5: 55220 | F5: 2025-01 | H5: Pays on time
A6: C05 | B6: Bluefjord Media | C6: UK | D6: Annual | E6: 40710 | F6: 2025-07 | H6: Pays on time
A7: C06 | B7: Quillmark Legal | C7: US | D7: Monthly | E7: 4370 | F7: 2024-11 | H7: Pays on time
A8: C07 | B8: Solace Fitness | C8: US | D8: Monthly | E8: 3660 | F8: 2025-02 | H8: Pays on time
A9: C08 | B9: Tidewater Credit Union | C9: US | D9: Monthly | E9: 8730 | F9: 2024-11 | H9: Pays on time
A10: C09 | B10: Ember Labs | C10: US | D10: Monthly | E10: 3070 | F10: 2025-06 | H10: Pays on time
A11: C10 | B11: Pinecrest Schools | C11: US | D11: Monthly | E11: 6140 | F11: 2025-09 | H11: Pays on time
A12: C11 | B12: Atlas Freight Partners | C12: US | D12: Monthly | E12: 17110 | F12: 2026-08 | H12: New large client (Aug 2026)
A13: C12 | B13: Kestrel Analytics | C13: Canada | D13: Monthly | E13: 6370 | F13: 2024-11 | H13: Pays on time
A14: C13 | B14: Orchard Robotics | C14: US | D14: Monthly | E14: 3420 | F14: 2026-03 | H14: Pays on time
